<?xml version="1.0" encoding="utf-8"?>
<HostedFunctionClass Name="HF_TRIAXIALACCELEROMETERCLASS" Guid="a91ffc0e0-50a0-4021-8f3e-6c8e7bf267b6a" XsdVersion="7.9" ATA="313100">
  <AnalogPort Name="ANA_OTriaxAnalogX" Guid="aed27298a-d2c2-413a-8b34-fe231f84b86da" Direction="Source" RefreshPeriod="70" RIUTemplate="40010" UDC="0-5Vdc">
    <AnalogSignalParameter Name="TriaxAccelX" Guid="a7383cbe9-806a-4e64-8a38-b0ab856e31afa" PublishedLatency="35" />
  </AnalogPort>
  <AnalogPort Name="ANA_OTriaxAnalogY" Guid="a34ea5384-bdc8-4e75-8f7e-336ad6dabb55a" Direction="Source" RefreshPeriod="70" RIUTemplate="40010" UDC="0-5Vdc">
    <AnalogSignalParameter Name="TriaxAccelY" Guid="a36a6f4f4-087e-4684-a774-b9da2a6a3e77a" PublishedLatency="35" />
  </AnalogPort>
  <AnalogPort Name="ANA_OTriaxZ" Guid="a3603d4eb-10c5-4152-bce0-2ba2059f1b44a" Direction="Source" RefreshPeriod="70" RIUTemplate="40010" UDC="0-5Vdc">
    <AnalogSignalParameter Name="TriaxAccelZ" Guid="a3d4eaa4d-48c6-4eb0-83ef-3c891ce30521a" PublishedLatency="35" />
  </AnalogPort>
</HostedFunctionClass>