<?xml version="1.0" encoding="utf-8"?>
<RemoteGateway Name="RGW09_I_40005_HF_FTIS_LRM" Guid="aa3ee41f9-21c6-4d78-aa30-4a42b4cfba71a" XsdVersion="7.9" Hardware="RDIU_09">
  <A429Port Name="pi429_A1_HF_FTIS_LRM" Guid="aa6d8c3b1-3ad9-4e4e-b41a-b6798460d178a" ActivityTimeout="3200" Direction="Destination" Physical="RDIU_09.40005_B01" SamplePeriod="640">
    <Dataflow_Ref SrcName="HF_FTIS_LRM.po429_A1" SrcGuid="a11505533-7adf-4af0-952b-194969fb2b26a" />
  </A429Port>
  <A429Port Name="pi429_A1_BLOCK_HF_FTIS_LRM" Guid="a3ea8fc50-b40d-420c-8ac1-443fe9dd7f73a" ActivityTimeout="400" Direction="Destination" Physical="RDIU_09.40005_B01" SamplePeriod="80">
    <Dataflow_Ref SrcName="HF_FTIS_LRM.po429_A1_BLOCK" SrcGuid="ab32dbf33-8c98-485f-a289-53ee7aaedc8aa" />
  </A429Port>
  <HFQueuingPort Name="HFQ3_O_A664_po429_A1_BLOCK_Msg" Guid="adcb46930-8dc0-4154-9107-91355fb3aa40a" Direction="Source" MessageSize="12" Networks="Both" QueueLength="2" RefreshPeriod="80">
    <A664Message Name="po429_A1_BLOCK_Msg_Q_3" Guid="a64d53787-9eef-4d41-a65c-f2c13a45f85ea" EdeEnable="True" MessageOverhead="32" MessagePad="0" MessageSize="12" MsgDataProtocolType="A429 Block" SubVLID="3" TransmissionIntervalMinimum="100" VLID="33356">
      <DS Name="FSS1" Guid="a30bf5177-0cc3-4b91-9132-285520c962b8a" ByteOffsetFSF="0" ByteOffsetWithinMsg="4" DataSetSize="4" DsDataProtocolType="A664_FSS">
        <DP Name="FSB1" Guid="aaee674d7-f2ff-413c-8dd5-a68d866b773ea" BitOffsetWithinDS="24" DataFormatType="A664_FSB" ParameterSize="8" />
      </DS>
      <DS Name="L357_FTIS_Config" Guid="aa8c27073-fe89-4213-b43b-5990ae956962a" ByteOffsetFSF="4" ByteOffsetWithinMsg="8" DataSetSize="4" DsDataProtocolType="Parametric data">
        <A429Word Name="L357_FTIS_Config" Guid="a8f7381f8-2e82-418b-8cd5-4acef7937bd8a" BitOffsetWithinDS="0">
          <DP Name="LABEL" Guid="afb969e68-0cb6-4af7-81ce-6b716522e8bca" BitOffsetWithinDS="0" DataFormatType="A429OCTLBL" Label="357" ParameterSize="8" PublishedLatency="100" TransmissionIntervalMinimum="100" />
          <DP Name="FTIS_A604_Config_Reply_Word" Guid="a22aa4c82-fba8-436f-9d7c-b72f8267ddb9a" BitOffsetWithinDS="8" DataFormatType="OPAQUE" ParameterSize="23" PublishedLatency="100" TransmissionIntervalMinimum="100" />
          <DP Name="PARITY" Guid="a4a6932a7-2bf3-48b2-8f27-57a984a9f301a" BitOffsetWithinDS="31" DataFormatType="A429PARITY" ParameterSize="1" PublishedLatency="100" TransmissionIntervalMinimum="100" />
          <Copy_Ref SrcName="HF_FTIS_LRM.po429_A1_BLOCK_Msg.L357_FTIS_Config" SrcGuid="a051c000f-bd49-4e77-86ca-b54c06ecf0efa" />
          <Gw_Pub_Ref DestName="HF_AHMUInstance.FUEL_FTIS_LRM_CONFIG_RPT_B" DestGuid="af89b8ced-7ea7-4605-af2a-dda039f9ffe8a" />
        </A429Word>
      </DS>
    </A664Message>
    <Gateway_Ref SrcName="RGW09_I_40005_HF_FTIS_LRM.pi429_A1_BLOCK_HF_FTIS_LRM" SrcGuid="a3ea8fc50-b40d-420c-8ac1-443fe9dd7f73a" />
  </HFQueuingPort>
  <HFSamplingPort Name="HFS1_O_A664_po429_A1_Msg" Guid="a81889d5c-442e-40e8-9e02-ea3396c7b13ca" Direction="Source" MessageSize="16" Networks="Both" RefreshPeriod="80">
    <A664Message Name="po429_A1_Msg_S_1" Guid="a13e48543-44fd-433e-8309-f6a0520da129a" EdeEnable="True" MessageOverhead="32" MessagePad="0" MessageSize="16" MsgDataProtocolType="Parametric data" SubVLID="1" TransmissionIntervalMinimum="1000" VLID="33356">
      <DS Name="FSS1" Guid="a83d19669-3d52-4d3a-93fe-f0e247957b3aa" ByteOffsetFSF="0" ByteOffsetWithinMsg="4" DataSetSize="4" DsDataProtocolType="A664_FSS">
        <DP Name="FSB1" Guid="ac66134ac-ceae-49d1-8f07-227355f7da53a" BitOffsetWithinDS="24" DataFormatType="A664_FSB" ParameterSize="8" />
        <DP Name="FSB2" Guid="a728faa21-5ff5-4b50-8eef-7aa7c5da065ea" BitOffsetWithinDS="16" DataFormatType="A664_FSB" ParameterSize="8" />
      </DS>
      <DS Name="L271_FTIS_CAS_Message" Guid="a95ceaa70-e4ed-4569-a3e7-867fe7c2e541a" ByteOffsetFSF="4" ByteOffsetWithinMsg="8" DataSetSize="4" DsDataProtocolType="Parametric data">
        <A429Word Name="L271_FTIS_CAS_Message" Guid="ac9fee0eb-83f9-4a7c-857b-f20263956583a" BitOffsetWithinDS="0">
          <DP Name="LABEL" Guid="ae364bc4e-2a3a-420e-838e-106602417e16a" BitOffsetWithinDS="0" DataFormatType="A429OCTLBL" Label="271" ParameterSize="8" PublishedLatency="1000" TransmissionIntervalMinimum="1000" />
          <DP Name="SDI" Guid="a5e3d3d12-722f-42ba-b10f-e1f4ca6f087ea" BitOffsetWithinDS="8" CodedSet="0=Invalid;1=FTIS LRM;2=Invalid;3=Invalid" DataFormatType="A429SDI" ParameterSize="2" PublishedLatency="1000" TransmissionIntervalMinimum="1000" />
          <DP Name="FTIS_ASM_HlthMon_TestsFailed" Guid="a583bec90-212c-4097-bed2-4c818370c138a" BitOffsetWithinDS="10" DataFormatType="DIS" OneState="1=TRUE" ParameterSize="1" PublishedLatency="1000" TransmissionIntervalMinimum="1000" ZeroState="0=FALSE">
            <Gw_Pub_Ref DestName="FDAS_L1.FTIS_LRM_A1_FTIS_ASM_HlthMon_TestsFailed_2" DestGuid="a7b0d7095-7891-4c0b-97b3-dbbd3977332ea" />
            <Gw_Pub_Ref DestName="FDAS_L3.FTIS_LRM_A1_FTIS_ASM_HlthMon_TestsFailed_2" DestGuid="aedb0c57f-a631-4da9-8df4-38a1e990f1c4a" />
            <Gw_Pub_Ref DestName="FDAS_R3.FTIS_LRM_A1_FTIS_ASM_HlthMon_TestsFailed_2" DestGuid="a2aee2e81-abd2-4ff1-9b1d-8469b6d26e7da" />
          </DP>
          <DP Name="FTIS_OvertempProtectRedundLoss" Guid="a6cf70887-ac9d-4f39-95d5-a62f5c075faba" BitOffsetWithinDS="11" DataFormatType="DIS" OneState="1=TRUE" ParameterSize="1" PublishedLatency="1000" TransmissionIntervalMinimum="1000" ZeroState="0=FALSE" />
          <DP Name="FTIS_Latched_Shutdown" Guid="aab82c1b5-8f4d-4187-bbd5-6b75fff4f019a" BitOffsetWithinDS="12" DataFormatType="DIS" OneState="1=TRUE" ParameterSize="1" PublishedLatency="1000" TransmissionIntervalMinimum="1000" ZeroState="0=FALSE" />
          <DP Name="Inerting_System_Inhibited" Guid="af9fdcd9c-1a74-4b09-936b-985b98ddec4ea" BitOffsetWithinDS="13" DataFormatType="DIS" OneState="1=TRUE" ParameterSize="1" PublishedLatency="1000" TransmissionIntervalMinimum="1000" ZeroState="0=FALSE" />
          <DP Name="ASM_Performance_Degraded" Guid="a6f2b3a0f-09b6-4212-8130-d32c67af3241a" BitOffsetWithinDS="14" DataFormatType="DIS" OneState="1=TRUE" ParameterSize="1" PublishedLatency="1000" TransmissionIntervalMinimum="1000" ZeroState="0=FALSE" />
          <DP Name="FTIS_Extemal_Fault" Guid="a200b6477-72e3-4cf7-b5db-e61a40c56215a" BitOffsetWithinDS="15" DataFormatType="DIS" OneState="1=TRUE" ParameterSize="1" PublishedLatency="1000" TransmissionIntervalMinimum="1000" ZeroState="0=FALSE" />
          <DP Name="SSM" Guid="a9f2b780d-6efc-4c47-a75b-f0b33fbffffca" BitOffsetWithinDS="29" DataFormatType="A429_SSM_DIS" ParameterSize="2" PublishedLatency="1000" TransmissionIntervalMinimum="1000" />
          <DP Name="PARITY" Guid="aec12d8b6-ce5b-431e-9466-b7f12dac901ea" BitOffsetWithinDS="31" DataFormatType="A429PARITY" ParameterSize="1" PublishedLatency="1000" TransmissionIntervalMinimum="1000" />
          <Copy_Ref SrcName="HF_FTIS_LRM.po429_A1_Msg.L271_FTIS_CAS_Message" SrcGuid="accc583d9-05c6-4423-84f4-29ef4d067466a" />
          <Gw_Pub_Ref DestName="PAA_L1Instance.L271_FTIS_Status_B1" DestGuid="a5da7c791-cb0d-4557-870a-d7b463cc8026a" />
        </A429Word>
      </DS>
      <DS Name="L336_FTIS_NEA_Oxyg_Concentration" Guid="aea37652a-6454-41c2-985d-8e800f59d669a" ByteOffsetFSF="5" ByteOffsetWithinMsg="12" DataSetSize="4" DsDataProtocolType="Parametric data">
        <A429Word Name="L336_FTIS_NEA_Oxyg_Concentration" Guid="ac07d9a3e-8a23-46a4-9a1b-594f38ef4326a" BitOffsetWithinDS="0">
          <DP Name="LABEL" Guid="a172dee84-741b-49b9-88dc-aa749f8ff83ca" BitOffsetWithinDS="0" DataFormatType="A429OCTLBL" Label="336" ParameterSize="8" PublishedLatency="1000" TransmissionIntervalMinimum="1000" />
          <DP Name="SDI" Guid="ac36c2db5-6900-4318-a4b4-2dc83f8d92eba" BitOffsetWithinDS="8" CodedSet="0=Invalid;1=FTIS LRM;2=Invalid;3=Invalid" DataFormatType="A429SDI" ParameterSize="2" PublishedLatency="1000" TransmissionIntervalMinimum="1000" />
          <DP Name="Percentage_Oxygen" Guid="abfedd3c7-4522-4c00-a619-c673a62e514aa" BitOffsetWithinDS="22" DataFormatType="BNR" FullScaleRngMax="127" FullScaleRngMin="-128" FuncRngMax="21" FuncRngMin="0" LsbRes="0.5" ParameterSize="7" PublishedLatency="1000" TransmissionIntervalMinimum="1000" Units="percent">
            <Gw_Pub_Ref DestName="SYNOPTICPAGEAPP_L.FTIS_B1_Percentage_Oxygen" DestGuid="a6bbf150f-460e-45f5-b9dd-bf2cee58d688a" />
            <Gw_Pub_Ref DestName="SYNOPTICPAGEAPP_R.FTIS_B1_Percentage_Oxygen" DestGuid="ad5e54936-21ed-4123-b279-9b056e16579ba" />
          </DP>
          <DP Name="SSM" Guid="af1bae7cd-ff8d-458e-8515-edd3b3b308d3a" BitOffsetWithinDS="29" DataFormatType="A429_SSM_BNR" ParameterSize="2" PublishedLatency="1000" TransmissionIntervalMinimum="1000" />
          <DP Name="PARITY" Guid="a843773bb-a384-44a9-8bb0-d76549fc93d2a" BitOffsetWithinDS="31" DataFormatType="A429PARITY" ParameterSize="1" PublishedLatency="1000" TransmissionIntervalMinimum="1000" />
          <Copy_Ref SrcName="HF_FTIS_LRM.po429_A1_Msg.L336_FTIS_NEA_Oxyg_Concentration" SrcGuid="aa99baefe-5976-4fa8-a430-571f1adaafeaa" />
        </A429Word>
      </DS>
    </A664Message>
    <Gateway_Ref SrcName="RGW09_I_40005_HF_FTIS_LRM.pi429_A1_HF_FTIS_LRM" SrcGuid="aa6d8c3b1-3ad9-4e4e-b41a-b6798460d178a" />
  </HFSamplingPort>
</RemoteGateway>