<?xml version="1.0" encoding="utf-8"?>
<RemoteGateway Name="RGW01_Analog_In_ATA42IMA" Guid="a726073d9-3d9d-4633-b0d4-98c23894ee5ea" XsdVersion="7.9" Hardware="RDIU_01">
  <AnalogPort Name="piDOP_Open_Gnd_01_HF_RDIU_01_AIRFRAME_TYPE" Guid="a86ed8206-22d3-4e64-a9cf-4c857616db15a" Direction="Destination" Physical="RDIU_01.40022_A19" RIUTemplate="40022" SamplePeriod="160" UDC="Confirmation period=2;Status inversion=2">
    <Dataflow_Ref SrcName="HF_RDIU_01_AIRFRAME_TYPE.poDISC_AirframeType_01" SrcGuid="a15112f43-6065-4664-b165-effae1c53e65a" />
  </AnalogPort>
  <AnalogPort Name="piDOP_Open_Gnd_02_HF_RDIU_01_AIRFRAME_TYPE" Guid="afa48976c-5994-4aea-808b-5b88c6374acba" Direction="Destination" Physical="RDIU_01.40022_A20" RIUTemplate="40022" SamplePeriod="160" UDC="Confirmation period=2;Status inversion=2">
    <Dataflow_Ref SrcName="HF_RDIU_01_AIRFRAME_TYPE.poDISC_AirframeType_02" SrcGuid="a068e55b9-71c5-4510-98b4-ee7e658194c8a" />
  </AnalogPort>
  <AnalogPort Name="piDOP_Open_Gnd_03_HF_RDIU_01_AIRFRAME_TYPE" Guid="a420faf97-9a6c-4d6a-ae90-37f63df7e108a" Direction="Destination" Physical="RDIU_01.40022_A21" RIUTemplate="40022" SamplePeriod="160" UDC="Confirmation period=2;Status inversion=2">
    <Dataflow_Ref SrcName="HF_RDIU_01_AIRFRAME_TYPE.poDISC_AirframeType_03" SrcGuid="a039b866e-1c19-4ff8-9151-a0bb27cb7fa5a" />
  </AnalogPort>
  <AnalogPort Name="piDOP_Open_Gnd_04_HF_RDIU_01_AIRFRAME_TYPE" Guid="aadad6419-4939-4b86-934c-b180ca756ab1a" Direction="Destination" Physical="RDIU_01.40022_A22" RIUTemplate="40022" SamplePeriod="160" UDC="Confirmation period=2;Status inversion=2">
    <Dataflow_Ref SrcName="HF_RDIU_01_AIRFRAME_TYPE.poDISC_AirframeType_04" SrcGuid="ae87d5271-333e-42fb-b61c-6e590343bd50a" />
  </AnalogPort>
  <AnalogPort Name="piDOP_Open_Gnd_05_HF_RDIU_01_AIRFRAME_TYPE" Guid="a941bcdf9-bfc3-4cdc-a556-03d6d9fd623da" Direction="Destination" Physical="RDIU_01.40022_A23" RIUTemplate="40022" SamplePeriod="160" UDC="Confirmation period=2;Status inversion=2">
    <Dataflow_Ref SrcName="HF_RDIU_01_AIRFRAME_TYPE.poDISC_AirframeType_05" SrcGuid="a1f0e79b4-53b6-45b9-a81e-90f9f4545907a" />
  </AnalogPort>
  <AnalogPort Name="piDOP_Open_Gnd_06_HF_RDIU_01_AIRFRAME_TYPE" Guid="a2302cb57-9d14-42de-9731-9bd656c9d85fa" Direction="Destination" Physical="RDIU_01.40022_A24" RIUTemplate="40022" SamplePeriod="160" UDC="Confirmation period=2;Status inversion=2">
    <Dataflow_Ref SrcName="HF_RDIU_01_AIRFRAME_TYPE.poDISC_AirframeType_06" SrcGuid="a8e5fd0a9-007f-4f3f-87a8-9f8253213394a" />
  </AnalogPort>
  <AnalogPort Name="piDOP_Open_Gnd_07_HF_RDIU_01_AIRFRAME_TYPE" Guid="ad55e2fa1-c9fb-4ac9-8ba7-fd0d3e345ce3a" Direction="Destination" Physical="RDIU_01.40022_A25" RIUTemplate="40022" SamplePeriod="160" UDC="Confirmation period=2;Status inversion=2">
    <Dataflow_Ref SrcName="HF_RDIU_01_AIRFRAME_TYPE.poDISC_AirframeType_07" SrcGuid="acfe63660-8376-4d57-a836-99a8dc275491a" />
  </AnalogPort>
  <AnalogPort Name="piDOP_Open_Gnd_08_HF_RDIU_01_AIRFRAME_TYPE" Guid="a093e85eb-29a0-4752-bcfb-7a55609b8761a" Direction="Destination" Physical="RDIU_01.40022_B01" RIUTemplate="40022" SamplePeriod="160" UDC="Confirmation period=2;Status inversion=2">
    <Dataflow_Ref SrcName="HF_RDIU_01_AIRFRAME_TYPE.poDISC_AirframeType_08" SrcGuid="ab04c1b2c-ee34-4dcf-8bbd-a5fa038045d0a" />
  </AnalogPort>
  <AnalogPort Name="piDOP_Open_Gnd_09_HF_RDIU_01_AIRFRAME_TYPE" Guid="aff92afbf-968c-44b9-82e9-2063bb7be708a" Direction="Destination" Physical="RDIU_01.40022_B02" RIUTemplate="40022" SamplePeriod="160" UDC="Confirmation period=2;Status inversion=2">
    <Dataflow_Ref SrcName="HF_RDIU_01_AIRFRAME_TYPE.poDISC_AirframeType_09" SrcGuid="a35afbb4e-4627-4ba5-a43a-663928adeeb8a" />
  </AnalogPort>
  <AnalogPort Name="piDOP_Open_Gnd_10_HF_RDIU_01_AIRFRAME_TYPE" Guid="a12afbd95-1051-497f-90a5-36f831520818a" Direction="Destination" Physical="RDIU_01.40022_B03" RIUTemplate="40022" SamplePeriod="160" UDC="Confirmation period=2;Status inversion=2">
    <Dataflow_Ref SrcName="HF_RDIU_01_AIRFRAME_TYPE.poDISC_AirframeType_10" SrcGuid="afc0d48b4-fda7-4c8e-b388-67caaa2b01e6a" />
  </AnalogPort>
  <AnalogPort Name="piDOP_Open_Gnd_11_HF_RDIU_01_AIRFRAME_TYPE" Guid="ae60b0c18-899d-4b24-b87c-2bd9a47a4119a" Direction="Destination" Physical="RDIU_01.40022_B04" RIUTemplate="40022" SamplePeriod="160" UDC="Confirmation period=2;Status inversion=2">
    <Dataflow_Ref SrcName="HF_RDIU_01_AIRFRAME_TYPE.poDISC_AirframeType_11" SrcGuid="a094c6224-d2ba-4892-834b-bbd7e9cd80c7a" />
  </AnalogPort>
  <AnalogPort Name="piDOP_Open_Gnd_12_HF_RDIU_01_AIRFRAME_TYPE" Guid="ad1ae927e-ecea-4874-a3d7-62948a3dc463a" Direction="Destination" Physical="RDIU_01.40022_B05" RIUTemplate="40022" SamplePeriod="160" UDC="Confirmation period=2;Status inversion=2">
    <Dataflow_Ref SrcName="HF_RDIU_01_AIRFRAME_TYPE.poDISC_AirframeType_12" SrcGuid="ae3636461-3d29-41a7-872d-ff42d860c633a" />
  </AnalogPort>
  <HFSamplingPort Name="HFS1_O_40022_ATA42IMA" Guid="a05006bc6-4327-45ff-97a9-cbf3e259553ca" Direction="Source" MessageSize="64" Networks="Both" RefreshPeriod="160">
    <A664Message Name="A664_O1_40022_ATA42IMA_Msg" Guid="a827f4403-c3ae-467b-ae02-a5351dacf98aa" EdeEnable="True" MessageOverhead="32" MessagePad="372" MessageSize="64" MsgDataProtocolType="Parametric data" SubVLID="2" TransmissionIntervalMinimum="1280" VLID="33400">
      <DS Name="FSS1" Guid="a575c37d6-8d2a-49e0-bd8a-bb86fff42707a" ByteOffsetFSF="0" ByteOffsetWithinMsg="4" DataSetSize="4" DsDataProtocolType="A664_FSS">
        <DP Name="FSB1" Guid="a72d2028b-d870-4072-82e5-e4ccb0aafa1fa" BitOffsetWithinDS="24" DataFormatType="A664_FSB" ParameterSize="8" />
        <DP Name="FSB2" Guid="af0f50b3e-da26-4858-b910-01913a94a59fa" BitOffsetWithinDS="16" DataFormatType="A664_FSB" ParameterSize="8" />
        <DP Name="FSB3" Guid="a3a394dab-8c9b-4612-b760-c29d60b80f98a" BitOffsetWithinDS="8" DataFormatType="A664_FSB" ParameterSize="8" />
        <DP Name="FSB4" Guid="ab2aa61c9-cce7-4e18-8c24-6861651917eba" BitOffsetWithinDS="0" DataFormatType="A664_FSB" ParameterSize="8" />
      </DS>
      <DS Name="AirframeType_01_HF_RDIU_01_AIRFRAME_TYPE" Guid="a85c32ed3-4203-46fe-89f8-a1d9967f6b08a" ByteOffsetFSF="4" ByteOffsetWithinMsg="8" DataSetSize="4" DsDataProtocolType="Parametric data">
        <DP Name="Status" Guid="a181ad5df-d3dd-4cf6-a9bf-04b0d696499ca" BitOffsetWithinDS="0" DataFormatType="DIS" ParameterSize="1" RIULabel="a" TransmissionIntervalMinimum="1280">
          <Copy_Ref SrcName="HF_RDIU_01_AIRFRAME_TYPE.AirframeType_01.Status" SrcGuid="ad6dbc7d5-4bde-4f4b-9aef-0f0c8fcb4843a" />
          <Gw_Pub_Ref DestName="HF_GIPC_A664_CH2.poDISC_AirframeType_01_Status" DestGuid="aa0fd20d0-fde2-4254-946f-36b5628e07a0a" />
          <Gw_Pub_Ref DestName="SM_I2C_L1.RDIU1_AircraftType_Discrete1" DestGuid="a54d8a59d-2a6e-4dd8-8c5d-7abb17fdb112a" />
          <Gw_Pub_Ref DestName="SM_I2C_L4.RDIU1_AircraftType_Discrete1" DestGuid="ad3d387f3-6b06-47cf-955b-042b488e3caaa" />
          <Gw_Pub_Ref DestName="SM_I2C_R1.RDIU1_AircraftType_Discrete1" DestGuid="ac324e333-b915-499d-ac16-26378b9a9e86a" />
          <Gw_Pub_Ref DestName="SM_I2C_R4.RDIU1_AircraftType_Discrete1" DestGuid="afc6677df-c5e5-4976-8259-84df9d254c51a" />
        </DP>
      </DS>
      <DS Name="AirframeType_02_HF_RDIU_01_AIRFRAME_TYPE" Guid="a1b20464d-3bb5-406f-a121-09771b881434a" ByteOffsetFSF="5" ByteOffsetWithinMsg="12" DataSetSize="4" DsDataProtocolType="Parametric data">
        <DP Name="Status" Guid="a83473bcc-fa45-41cb-90b5-a7680bfbf891a" BitOffsetWithinDS="0" DataFormatType="DIS" ParameterSize="1" RIULabel="a" TransmissionIntervalMinimum="1280">
          <Copy_Ref SrcName="HF_RDIU_01_AIRFRAME_TYPE.AirframeType_02.Status" SrcGuid="a6cd20e16-c2af-4db3-809f-d198db5d33eba" />
          <Gw_Pub_Ref DestName="HF_GIPC_A664_CH2.poDISC_AirframeType_02_Status" DestGuid="afca9c587-e6e2-4f0e-a342-f64c3464ffffa" />
          <Gw_Pub_Ref DestName="SM_I2C_L1.RDIU1_AircraftType_Discrete2" DestGuid="a9f875cc2-b295-49cf-bfd6-cdd843e2f28ba" />
          <Gw_Pub_Ref DestName="SM_I2C_L4.RDIU1_AircraftType_Discrete2" DestGuid="a192213fe-7922-4cb6-b1a0-8a4e7a88002fa" />
          <Gw_Pub_Ref DestName="SM_I2C_R1.RDIU1_AircraftType_Discrete2" DestGuid="a18735943-9aa1-4b1f-934c-8ce80847bfbea" />
          <Gw_Pub_Ref DestName="SM_I2C_R4.RDIU1_AircraftType_Discrete2" DestGuid="a169c16ea-76e8-43c9-a2cf-52166cef9414a" />
        </DP>
      </DS>
      <DS Name="AirframeType_03_HF_RDIU_01_AIRFRAME_TYPE" Guid="a7d749f34-7000-4bda-908b-affce5e178dfa" ByteOffsetFSF="6" ByteOffsetWithinMsg="16" DataSetSize="4" DsDataProtocolType="Parametric data">
        <DP Name="Status" Guid="aadb05a0c-ab9f-4a07-aeb4-516638a9e86aa" BitOffsetWithinDS="0" DataFormatType="DIS" ParameterSize="1" RIULabel="a" TransmissionIntervalMinimum="1280">
          <Copy_Ref SrcName="HF_RDIU_01_AIRFRAME_TYPE.AirframeType_03.Status" SrcGuid="ad1fa2e6c-7b2c-44a3-a3aa-b805ae659b60a" />
          <Gw_Pub_Ref DestName="HF_GIPC_A664_CH2.poDISC_AirframeType_03_Status" DestGuid="ab93d112f-78b3-43cb-967e-5690988f2f2aa" />
          <Gw_Pub_Ref DestName="SM_I2C_L1.RDIU1_AircraftType_Discrete3" DestGuid="a71ac1b23-0606-4a7d-bb2f-b2266dbc4b12a" />
          <Gw_Pub_Ref DestName="SM_I2C_L4.RDIU1_AircraftType_Discrete3" DestGuid="ab32e46ca-05ef-47f2-abfd-3e5dab9f67faa" />
          <Gw_Pub_Ref DestName="SM_I2C_R1.RDIU1_AircraftType_Discrete3" DestGuid="a94416c09-aa58-4eb2-92f3-ced6a9f83b56a" />
          <Gw_Pub_Ref DestName="SM_I2C_R4.RDIU1_AircraftType_Discrete3" DestGuid="a8539af88-95db-413a-ab69-b0d4611a472fa" />
        </DP>
      </DS>
      <DS Name="AirframeType_04_HF_RDIU_01_AIRFRAME_TYPE" Guid="a4eb14b05-4d23-48aa-ad2e-2d3430dc564aa" ByteOffsetFSF="7" ByteOffsetWithinMsg="20" DataSetSize="4" DsDataProtocolType="Parametric data">
        <DP Name="Status" Guid="af4443db0-f08f-4da1-a605-f26c5f672ba1a" BitOffsetWithinDS="0" DataFormatType="DIS" ParameterSize="1" RIULabel="a" TransmissionIntervalMinimum="1280">
          <Copy_Ref SrcName="HF_RDIU_01_AIRFRAME_TYPE.AirframeType_04.Status" SrcGuid="a929eb91a-f7f0-47b0-b048-19e514652d26a" />
          <Gw_Pub_Ref DestName="HF_GIPC_A664_CH2.poDISC_AirframeType_04_Status" DestGuid="ae9707212-4c48-4f08-8873-6f76db961244a" />
          <Gw_Pub_Ref DestName="SM_I2C_L1.RDIU1_AircraftType_Discrete4" DestGuid="ac6ad28f4-87f4-449c-b8b2-9ad82f67f8d6a" />
          <Gw_Pub_Ref DestName="SM_I2C_L4.RDIU1_AircraftType_Discrete4" DestGuid="a7714a9c4-85e0-48b4-bbfa-9565a2e8d89ba" />
          <Gw_Pub_Ref DestName="SM_I2C_R1.RDIU1_AircraftType_Discrete4" DestGuid="a6608ba50-ccff-4590-a834-e400837461d2a" />
          <Gw_Pub_Ref DestName="SM_I2C_R4.RDIU1_AircraftType_Discrete4" DestGuid="a84ba4f47-4167-4e2d-a09f-67478e372eaaa" />
        </DP>
      </DS>
      <DS Name="FSS2" Guid="a3c1f0b61-5e6d-424d-adde-134ff5811fdea" ByteOffsetFSF="0" ByteOffsetWithinMsg="24" DataSetSize="4" DsDataProtocolType="A664_FSS">
        <DP Name="FSB5" Guid="a7d9aaac2-07b2-4d09-ae99-2ff80585b09aa" BitOffsetWithinDS="24" DataFormatType="A664_FSB" ParameterSize="8" />
        <DP Name="FSB6" Guid="a778729c0-81f2-4ffc-8814-645fb19382eaa" BitOffsetWithinDS="16" DataFormatType="A664_FSB" ParameterSize="8" />
        <DP Name="FSB7" Guid="a53d1163d-c176-490a-940e-90719f1c78e7a" BitOffsetWithinDS="8" DataFormatType="A664_FSB" ParameterSize="8" />
        <DP Name="FSB8" Guid="a0e35849f-0069-4435-a300-3a29e261f10fa" BitOffsetWithinDS="0" DataFormatType="A664_FSB" ParameterSize="8" />
      </DS>
      <DS Name="AirframeType_05_HF_RDIU_01_AIRFRAME_TYPE" Guid="af0395585-466f-46d7-9ab3-74cec8d48396a" ByteOffsetFSF="24" ByteOffsetWithinMsg="28" DataSetSize="4" DsDataProtocolType="Parametric data">
        <DP Name="Status" Guid="ae2fd782d-e737-4e46-bb49-33f982daeb7da" BitOffsetWithinDS="0" DataFormatType="DIS" ParameterSize="1" RIULabel="a" TransmissionIntervalMinimum="1280">
          <Copy_Ref SrcName="HF_RDIU_01_AIRFRAME_TYPE.AirframeType_05.Status" SrcGuid="aa17079cb-9af7-40b5-8bcd-929c9089842ea" />
          <Gw_Pub_Ref DestName="HF_GIPC_A664_CH2.poDISC_AirframeType_05_Status" DestGuid="a77c0cbed-692b-48b3-8fcb-02ed443e2d90a" />
          <Gw_Pub_Ref DestName="SM_I2C_L1.RDIU1_AircraftType_Discrete5" DestGuid="afb519723-f0dc-4c05-92fb-78ef88fd5446a" />
          <Gw_Pub_Ref DestName="SM_I2C_L4.RDIU1_AircraftType_Discrete5" DestGuid="a1268e751-bbed-4ee4-b7cc-246d713387fea" />
          <Gw_Pub_Ref DestName="SM_I2C_R1.RDIU1_AircraftType_Discrete5" DestGuid="a5b386666-61fa-4c9a-b3b9-26b7072f94cda" />
          <Gw_Pub_Ref DestName="SM_I2C_R4.RDIU1_AircraftType_Discrete5" DestGuid="a5476f407-49c7-4f03-ad4d-50df18b72ce3a" />
        </DP>
      </DS>
      <DS Name="AirframeType_06_HF_RDIU_01_AIRFRAME_TYPE" Guid="a6d59b870-b3e1-453e-9f21-46979a33f72fa" ByteOffsetFSF="25" ByteOffsetWithinMsg="32" DataSetSize="4" DsDataProtocolType="Parametric data">
        <DP Name="Status" Guid="a87c0ccb8-44eb-4e6e-875e-ba1e40f919bca" BitOffsetWithinDS="0" DataFormatType="DIS" ParameterSize="1" RIULabel="a" TransmissionIntervalMinimum="1280">
          <Copy_Ref SrcName="HF_RDIU_01_AIRFRAME_TYPE.AirframeType_06.Status" SrcGuid="aa27d2c5c-bc1d-45ef-ad13-f0bb0d84bd2ba" />
          <Gw_Pub_Ref DestName="HF_GIPC_A664_CH2.poDISC_AirframeType_06_Status" DestGuid="adf7ab37c-3d1c-49bc-bfb6-3f9a9712439aa" />
          <Gw_Pub_Ref DestName="SM_I2C_L1.RDIU1_AircraftType_Discrete6" DestGuid="ac9a6f009-227d-43f4-9e21-9c9a53540255a" />
          <Gw_Pub_Ref DestName="SM_I2C_L4.RDIU1_AircraftType_Discrete6" DestGuid="adc539b74-cd0c-4b63-b076-21b1613d1d51a" />
          <Gw_Pub_Ref DestName="SM_I2C_R1.RDIU1_AircraftType_Discrete6" DestGuid="ae57576e5-4e02-4f8b-91d1-f3cf93ad4791a" />
          <Gw_Pub_Ref DestName="SM_I2C_R4.RDIU1_AircraftType_Discrete6" DestGuid="a1539043b-db9a-48fc-bceb-5f9c7db0e699a" />
        </DP>
      </DS>
      <DS Name="AirframeType_07_HF_RDIU_01_AIRFRAME_TYPE" Guid="a48ee12e9-ce28-40f1-865a-2224e87c699da" ByteOffsetFSF="26" ByteOffsetWithinMsg="36" DataSetSize="4" DsDataProtocolType="Parametric data">
        <DP Name="Status" Guid="ad564b8da-225d-47de-a048-363008abe312a" BitOffsetWithinDS="0" DataFormatType="DIS" ParameterSize="1" RIULabel="a" TransmissionIntervalMinimum="1280">
          <Copy_Ref SrcName="HF_RDIU_01_AIRFRAME_TYPE.AirframeType_07.Status" SrcGuid="a27bc54ef-8c9c-4f45-b9dd-9e7c26dd49c6a" />
          <Gw_Pub_Ref DestName="HF_GIPC_A664_CH2.poDISC_AirframeType_07_Status" DestGuid="a07b6b8da-3eab-4115-9876-e8681d523695a" />
          <Gw_Pub_Ref DestName="SM_I2C_L1.RDIU1_AircraftType_Discrete7" DestGuid="aeeab193a-40f4-48ed-9739-ff177de156cba" />
          <Gw_Pub_Ref DestName="SM_I2C_L4.RDIU1_AircraftType_Discrete7" DestGuid="acc8b8f4e-d88e-4c60-884f-6978902db0b0a" />
          <Gw_Pub_Ref DestName="SM_I2C_R1.RDIU1_AircraftType_Discrete7" DestGuid="aacbf3d0e-9447-472a-8158-26d0519b545ca" />
          <Gw_Pub_Ref DestName="SM_I2C_R4.RDIU1_AircraftType_Discrete7" DestGuid="a4aadd7ed-ba9e-4467-90db-7274698ab7d4a" />
        </DP>
      </DS>
      <DS Name="AirframeType_08_HF_RDIU_01_AIRFRAME_TYPE" Guid="ae8fb92d0-047e-4942-b607-f26ea1f10c14a" ByteOffsetFSF="27" ByteOffsetWithinMsg="40" DataSetSize="4" DsDataProtocolType="Parametric data">
        <DP Name="Status" Guid="aa67172ce-5dcb-437e-86c2-c33ab9c19e61a" BitOffsetWithinDS="0" DataFormatType="DIS" ParameterSize="1" RIULabel="a" TransmissionIntervalMinimum="1280">
          <Copy_Ref SrcName="HF_RDIU_01_AIRFRAME_TYPE.AirframeType_08.Status" SrcGuid="aebf5c2db-601a-4caa-b1e1-cb493401067ca" />
          <Gw_Pub_Ref DestName="HF_GIPC_A664_CH2.poDISC_AirframeType_08_Status" DestGuid="a7a30de76-a8fd-4a4a-a611-a9efabba86b0a" />
          <Gw_Pub_Ref DestName="SM_I2C_L1.RDIU1_AircraftType_Discrete8" DestGuid="acefdbf2d-42e3-4676-a959-8180e846aa5da" />
          <Gw_Pub_Ref DestName="SM_I2C_L4.RDIU1_AircraftType_Discrete8" DestGuid="adcb7cbae-eed3-4d5f-b628-c26676d49295a" />
          <Gw_Pub_Ref DestName="SM_I2C_R1.RDIU1_AircraftType_Discrete8" DestGuid="ab2f1bff9-785f-4499-b2e6-519aa0a7703ea" />
          <Gw_Pub_Ref DestName="SM_I2C_R4.RDIU1_AircraftType_Discrete8" DestGuid="a2df4f28e-17e4-4388-b4e6-c10be508d244a" />
        </DP>
      </DS>
      <DS Name="FSS3" Guid="ad479cc16-3e7c-44af-b4e1-b2c193b3704ba" ByteOffsetFSF="0" ByteOffsetWithinMsg="44" DataSetSize="4" DsDataProtocolType="A664_FSS">
        <DP Name="FSB9" Guid="a69806e84-9268-4fee-b8aa-c20ebc1dc09da" BitOffsetWithinDS="24" DataFormatType="A664_FSB" ParameterSize="8" />
        <DP Name="FSB10" Guid="a8ef3f2e3-994d-44dc-8d7d-36aa53ede807a" BitOffsetWithinDS="16" DataFormatType="A664_FSB" ParameterSize="8" />
        <DP Name="FSB11" Guid="aada86bc1-56a4-43c4-82dc-09405200872fa" BitOffsetWithinDS="8" DataFormatType="A664_FSB" ParameterSize="8" />
        <DP Name="FSB12" Guid="af1e91b62-cd4a-4b8a-b0e3-c385260f2822a" BitOffsetWithinDS="0" DataFormatType="A664_FSB" ParameterSize="8" />
      </DS>
      <DS Name="AirframeType_09_HF_RDIU_01_AIRFRAME_TYPE" Guid="ae122ecce-faad-44b1-ba46-8b3bb4cd0154a" ByteOffsetFSF="44" ByteOffsetWithinMsg="48" DataSetSize="4" DsDataProtocolType="Parametric data">
        <DP Name="Status" Guid="a89ecc7b0-e3c2-4e40-90e0-20dc8c28877ca" BitOffsetWithinDS="0" DataFormatType="DIS" ParameterSize="1" RIULabel="a" TransmissionIntervalMinimum="1280">
          <Copy_Ref SrcName="HF_RDIU_01_AIRFRAME_TYPE.AirframeType_09.Status" SrcGuid="ac36799cb-4cc1-4c72-a44f-273cf4f0e33ca" />
          <Gw_Pub_Ref DestName="HF_GIPC_A664_CH2.poDISC_AirframeType_09_Status" DestGuid="a7617de2c-dedc-4231-bb0f-03cf75c3e940a" />
          <Gw_Pub_Ref DestName="SM_I2C_L1.RDIU1_AircraftType_Discrete9" DestGuid="ae48d07ac-4922-46cc-9a8e-0197a6214e65a" />
          <Gw_Pub_Ref DestName="SM_I2C_L4.RDIU1_AircraftType_Discrete9" DestGuid="abb6258fc-3c76-47d6-ac54-c2e5e867097ca" />
          <Gw_Pub_Ref DestName="SM_I2C_R1.RDIU1_AircraftType_Discrete9" DestGuid="ae2961ffb-b9db-41fd-95dd-b17e2237eb47a" />
          <Gw_Pub_Ref DestName="SM_I2C_R4.RDIU1_AircraftType_Discrete9" DestGuid="ab3b88f4e-a187-48d8-ab5b-4e481b14b6e7a" />
        </DP>
      </DS>
      <DS Name="AirframeType_10_HF_RDIU_01_AIRFRAME_TYPE" Guid="aadb8d678-fd94-4243-be2d-3dcfff9421dca" ByteOffsetFSF="45" ByteOffsetWithinMsg="52" DataSetSize="4" DsDataProtocolType="Parametric data">
        <DP Name="Status" Guid="a936aebf9-a1d2-4b72-9008-82c01c0629e6a" BitOffsetWithinDS="0" DataFormatType="DIS" ParameterSize="1" RIULabel="a" TransmissionIntervalMinimum="1280">
          <Copy_Ref SrcName="HF_RDIU_01_AIRFRAME_TYPE.AirframeType_10.Status" SrcGuid="ad4fe20da-0a74-45e9-ac7c-da956325693ca" />
          <Gw_Pub_Ref DestName="HF_GIPC_A664_CH2.poDISC_AirframeType_10_Status" DestGuid="ab98f5106-a703-40d7-a13d-f537758894a8a" />
          <Gw_Pub_Ref DestName="SM_I2C_L1.RDIU1_AircraftType_Discrete10" DestGuid="ac554cdb4-9119-4352-b98f-475d3d315075a" />
          <Gw_Pub_Ref DestName="SM_I2C_L4.RDIU1_AircraftType_Discrete10" DestGuid="a997b3f6a-a0f7-4403-a95b-d1c62ee93cafa" />
          <Gw_Pub_Ref DestName="SM_I2C_R1.RDIU1_AircraftType_Discrete10" DestGuid="aa5dac09b-d8b5-4c9c-bbb5-924ee271790aa" />
          <Gw_Pub_Ref DestName="SM_I2C_R4.RDIU1_AircraftType_Discrete10" DestGuid="ac0dabcba-788c-4fd9-863e-ecdc08dce448a" />
        </DP>
      </DS>
      <DS Name="AirframeType_11_HF_RDIU_01_AIRFRAME_TYPE" Guid="acf0c3c84-dff5-4a8d-beb6-a3e4cfe6528da" ByteOffsetFSF="46" ByteOffsetWithinMsg="56" DataSetSize="4" DsDataProtocolType="Parametric data">
        <DP Name="Status" Guid="a17f19621-cf4d-4d22-b5cd-424e8fc60c7fa" BitOffsetWithinDS="0" DataFormatType="DIS" ParameterSize="1" RIULabel="a" TransmissionIntervalMinimum="1280">
          <Copy_Ref SrcName="HF_RDIU_01_AIRFRAME_TYPE.AirframeType_11.Status" SrcGuid="a4d1b329b-dae1-40c7-bca0-76e974918eb4a" />
          <Gw_Pub_Ref DestName="HF_GIPC_A664_CH2.poDISC_AirframeType_11_Status" DestGuid="acb5d39d1-3e10-4ddf-9fe2-8294c910d08ca" />
          <Gw_Pub_Ref DestName="SM_I2C_L1.RDIU1_AircraftType_Discrete11" DestGuid="a8b89115f-9e75-418b-9479-9734d4594849a" />
          <Gw_Pub_Ref DestName="SM_I2C_L4.RDIU1_AircraftType_Discrete11" DestGuid="ab7b2159c-1e09-410a-9059-5f77da632221a" />
          <Gw_Pub_Ref DestName="SM_I2C_R1.RDIU1_AircraftType_Discrete11" DestGuid="ae8cf5334-4113-40dd-ba46-594a355f481ba" />
          <Gw_Pub_Ref DestName="SM_I2C_R4.RDIU1_AircraftType_Discrete11" DestGuid="a8a204d7e-cbb7-452a-a8ca-083d5012d467a" />
        </DP>
      </DS>
      <DS Name="AirframeType_12_HF_RDIU_01_AIRFRAME_TYPE" Guid="a5350c2f2-8301-4ce9-8aee-bed4eb6829f8a" ByteOffsetFSF="47" ByteOffsetWithinMsg="60" DataSetSize="4" DsDataProtocolType="Parametric data">
        <DP Name="Status" Guid="a0fb990b2-c15e-4621-af75-6909bf953318a" BitOffsetWithinDS="0" DataFormatType="DIS" ParameterSize="1" RIULabel="a" TransmissionIntervalMinimum="1280">
          <Copy_Ref SrcName="HF_RDIU_01_AIRFRAME_TYPE.AirframeType_12.Status" SrcGuid="a9f7adb08-e371-4faf-9652-cde5fa8d59c6a" />
          <Gw_Pub_Ref DestName="HF_GIPC_A664_CH2.poDISC_AirframeType_12_Status" DestGuid="a3ef2fd25-0d94-4b0d-b857-8cb4fc070882a" />
          <Gw_Pub_Ref DestName="SM_I2C_L1.RDIU1_AircraftType_Discrete12" DestGuid="a059bf1dc-cf1f-4bc3-83a8-de316060e09aa" />
          <Gw_Pub_Ref DestName="SM_I2C_L4.RDIU1_AircraftType_Discrete12" DestGuid="afb99ba36-dd53-4d6f-8964-10546832634ba" />
          <Gw_Pub_Ref DestName="SM_I2C_R1.RDIU1_AircraftType_Discrete12" DestGuid="a779e7f89-70c8-416f-aecc-16e98838fa93a" />
          <Gw_Pub_Ref DestName="SM_I2C_R4.RDIU1_AircraftType_Discrete12" DestGuid="a04a940c9-f226-4532-9eb2-8eb910d95f74a" />
        </DP>
      </DS>
    </A664Message>
    <Gateway_Ref SrcName="RGW01_Analog_In_ATA42IMA.piDOP_Open_Gnd_01_HF_RDIU_01_AIRFRAME_TYPE" SrcGuid="a86ed8206-22d3-4e64-a9cf-4c857616db15a" />
    <Gateway_Ref SrcName="RGW01_Analog_In_ATA42IMA.piDOP_Open_Gnd_02_HF_RDIU_01_AIRFRAME_TYPE" SrcGuid="afa48976c-5994-4aea-808b-5b88c6374acba" />
    <Gateway_Ref SrcName="RGW01_Analog_In_ATA42IMA.piDOP_Open_Gnd_03_HF_RDIU_01_AIRFRAME_TYPE" SrcGuid="a420faf97-9a6c-4d6a-ae90-37f63df7e108a" />
    <Gateway_Ref SrcName="RGW01_Analog_In_ATA42IMA.piDOP_Open_Gnd_04_HF_RDIU_01_AIRFRAME_TYPE" SrcGuid="aadad6419-4939-4b86-934c-b180ca756ab1a" />
    <Gateway_Ref SrcName="RGW01_Analog_In_ATA42IMA.piDOP_Open_Gnd_05_HF_RDIU_01_AIRFRAME_TYPE" SrcGuid="a941bcdf9-bfc3-4cdc-a556-03d6d9fd623da" />
    <Gateway_Ref SrcName="RGW01_Analog_In_ATA42IMA.piDOP_Open_Gnd_06_HF_RDIU_01_AIRFRAME_TYPE" SrcGuid="a2302cb57-9d14-42de-9731-9bd656c9d85fa" />
    <Gateway_Ref SrcName="RGW01_Analog_In_ATA42IMA.piDOP_Open_Gnd_07_HF_RDIU_01_AIRFRAME_TYPE" SrcGuid="ad55e2fa1-c9fb-4ac9-8ba7-fd0d3e345ce3a" />
    <Gateway_Ref SrcName="RGW01_Analog_In_ATA42IMA.piDOP_Open_Gnd_08_HF_RDIU_01_AIRFRAME_TYPE" SrcGuid="a093e85eb-29a0-4752-bcfb-7a55609b8761a" />
    <Gateway_Ref SrcName="RGW01_Analog_In_ATA42IMA.piDOP_Open_Gnd_09_HF_RDIU_01_AIRFRAME_TYPE" SrcGuid="aff92afbf-968c-44b9-82e9-2063bb7be708a" />
    <Gateway_Ref SrcName="RGW01_Analog_In_ATA42IMA.piDOP_Open_Gnd_10_HF_RDIU_01_AIRFRAME_TYPE" SrcGuid="a12afbd95-1051-497f-90a5-36f831520818a" />
    <Gateway_Ref SrcName="RGW01_Analog_In_ATA42IMA.piDOP_Open_Gnd_11_HF_RDIU_01_AIRFRAME_TYPE" SrcGuid="ae60b0c18-899d-4b24-b87c-2bd9a47a4119a" />
    <Gateway_Ref SrcName="RGW01_Analog_In_ATA42IMA.piDOP_Open_Gnd_12_HF_RDIU_01_AIRFRAME_TYPE" SrcGuid="ad1ae927e-ecea-4874-a3d7-62948a3dc463a" />
  </HFSamplingPort>
</RemoteGateway>