<?xml version="1.0" encoding="utf-8"?>
<EmbFcn Name="EF_FWD_BBSOV_RELAY" Guid="a3a783937-9a32-4cf1-b125-b400c69f2f53a" XsdVersion="7.9" ChangeAuthority="UnknownOwner" DiagramFile="C:\Program Files (x86)\GE Aviation\EFE Toolset\ApplicationResource\Layout Files\a3a783937-9a32-4cf1-b125-b400c69f2f53a.efl" DiagramMD5="RjM4NTEyMjZCMkI0RjkyNkZDODYzMkVGNjI0NTU0NDQ=" UpdatePeriod="320">
  <DataInPort Name="BBSOV_RELAY_CMD_IASC1A" Guid="a83467da8-b203-453a-8afc-b434bde56b17a" DataFormatType="DIS" ParameterSize="1">
    <Emb_Ref SrcName="HF_IASC1.po429_OA_Msg_500.L304_External_Command_Word.BBSOV_RELAY_CMD" SrcGuid="af4824c60-7a5b-4155-b49d-641d288c7756a" />
  </DataInPort>
  <DesignConstant Name="DIS1_ZERO_ND" Guid="a36540353-C944-437c-B3D2-EA5145007329a" DataFormatType="DIS" ParameterSize="1" />
  <DataInPort Name="BBSOV_RELAY_CMD_IASC1B" Guid="a22d5cdd4-7f99-4579-8cda-4f1fda1426e7a" DataFormatType="DIS" ParameterSize="1">
    <Emb_Ref SrcName="HF_IASC1.po429_OB_Msg_500.L304_External_Command_Word.BBSOV_RELAY_CMD" SrcGuid="a28e0958c-042b-4710-9cf8-824988e0e51da" />
  </DataInPort>
  <DataOutPort Name="FWD_BBSOV_RELAY_CMD" Guid="a813a492d-133d-44eb-a16f-014f127d8a8ba" DataFormatType="DIS" ParameterSize="1">
    <Trans_Ref SrcName="EF_FWD_BBSOV_RELAY.INSTANCE_3.Output" SrcGuid="ac17a00bd-e361-4375-9bd0-75531128350ba" />
  </DataOutPort>
  <TransFcn Name="INSTANCE_1" Guid="a901a47b7-0fa7-46c2-98fa-ee0e288f9daca" RIUTemplate="41065" SequenceNumber="1" TemplateInstance="41065_T01" UDC="Logic=2;Acknowledge Time=500;Hold Time=500;">
    <DataInPort Name="Input_1" Guid="a4d23333c-e28f-4e26-86c4-3d0fea1cfe08a" DataFormatType="DIS" ParameterSize="1" RIULabel="a">
      <Trans_Ref SrcName="EF_FWD_BBSOV_RELAY.BBSOV_RELAY_CMD_IASC1A" SrcGuid="a83467da8-b203-453a-8afc-b434bde56b17a" />
    </DataInPort>
    <DataInPort Name="Input_2" Guid="ad9e87def-a0a4-4faf-8a8d-9d676eaa1e34a" DataFormatType="DIS" ParameterSize="1" RIULabel="b">
      <Trans_Ref SrcName="EF_FWD_BBSOV_RELAY.BBSOV_RELAY_CMD_IASC1B" SrcGuid="a22d5cdd4-7f99-4579-8cda-4f1fda1426e7a" />
    </DataInPort>
    <DataOutPort Name="Output" Guid="a43ea5f47-d62a-4834-b77b-e239a06224afa" DataFormatType="DIS" ParameterSize="1" RIULabel="c" />
  </TransFcn>
  <TransFcn Name="INSTANCE_2" Guid="a05a18fe1-1a5d-46bf-8216-6fc54b20eb0ea" RIUTemplate="41071" SequenceNumber="2" TemplateInstance="41071_T01" UDC="Mode=2;">
    <DataInPort Name="Input_1" Guid="ab7ac7dbc-5668-44a7-905e-d18876432875a" DataFormatType="DIS" ParameterSize="1" RIULabel="a">
      <Trans_Ref SrcName="EF_FWD_BBSOV_RELAY.BBSOV_RELAY_CMD_IASC1A" SrcGuid="a83467da8-b203-453a-8afc-b434bde56b17a" />
    </DataInPort>
    <DataInPort Name="Input_2" Guid="a24d42968-bd91-4d67-969c-20618f94b3e4a" DataFormatType="DIS" ParameterSize="1" RIULabel="b">
      <Trans_Ref SrcName="EF_FWD_BBSOV_RELAY.BBSOV_RELAY_CMD_IASC1B" SrcGuid="a22d5cdd4-7f99-4579-8cda-4f1fda1426e7a" />
    </DataInPort>
    <DataInPort Name="Input_3" Guid="abb13245c-599e-450e-b1d6-7524bfe05e04a" DataFormatType="DIS" ParameterSize="1" RIULabel="c">
      <Trans_Ref SrcName="EF_FWD_BBSOV_RELAY.DIS1_ZERO_ND" SrcGuid="a36540353-C944-437c-B3D2-EA5145007329a" Validated="-1" />
    </DataInPort>
    <DataInPort Name="Input_4" Guid="a87c62fc3-3e50-481c-9e94-4e008ca53f9da" DataFormatType="DIS" ParameterSize="1" RIULabel="d">
      <Trans_Ref SrcName="EF_FWD_BBSOV_RELAY.DIS1_ZERO_ND" SrcGuid="a36540353-C944-437c-B3D2-EA5145007329a" Validated="-1" />
    </DataInPort>
    <DataOutPort Name="Output" Guid="a4ed5c29e-ec5b-4cfe-a523-52d58d0be8c9a" DataFormatType="DIS" ParameterSize="1" RIULabel="e" />
  </TransFcn>
  <TransFcn Name="INSTANCE_3" Guid="a8ab72df1-bce2-4369-b0c9-694bb51fa4bda" RIUTemplate="41071" SequenceNumber="3" TemplateInstance="41071_T01" UDC="Mode=2;">
    <DataInPort Name="Input_1" Guid="abdc78004-ed3c-45e9-a36c-699550f74687a" DataFormatType="DIS" ParameterSize="1" RIULabel="a">
      <Trans_Ref SrcName="EF_FWD_BBSOV_RELAY.INSTANCE_1.Output" SrcGuid="a43ea5f47-d62a-4834-b77b-e239a06224afa" />
    </DataInPort>
    <DataInPort Name="Input_2" Guid="afa6c8c3e-6e1d-41e8-8f5c-0a78aafdc424a" DataFormatType="DIS" ParameterSize="1" RIULabel="b">
      <Trans_Ref SrcName="EF_FWD_BBSOV_RELAY.INSTANCE_2.Output" SrcGuid="a4ed5c29e-ec5b-4cfe-a523-52d58d0be8c9a" />
    </DataInPort>
    <DataInPort Name="Input_3" Guid="a9c5bf453-74a5-4f58-b029-bffa484b0fb3a" DataFormatType="DIS" ParameterSize="1" RIULabel="c">
      <Trans_Ref SrcName="EF_FWD_BBSOV_RELAY.DIS1_ZERO_ND" SrcGuid="a36540353-C944-437c-B3D2-EA5145007329a" Validated="-1" />
    </DataInPort>
    <DataInPort Name="Input_4" Guid="aa7357e41-21cf-42d8-b020-63005adccceea" DataFormatType="DIS" ParameterSize="1" RIULabel="d">
      <Trans_Ref SrcName="EF_FWD_BBSOV_RELAY.DIS1_ZERO_ND" SrcGuid="a36540353-C944-437c-B3D2-EA5145007329a" Validated="-1" />
    </DataInPort>
    <DataOutPort Name="Output" Guid="ac17a00bd-e361-4375-9bd0-75531128350ba" DataFormatType="DIS" ParameterSize="1" RIULabel="e" />
  </TransFcn>
</EmbFcn>