<A664ApplicationPorts>
        <SamplingPort 
            Name="IP_SP_FDAS_PEERB_XTALK"  
            Attribute="LOCAL_PORT"
            Direction="DESTINATION"
            MessageSize="96"
            RefreshRate="0.05"/>
        
        <SamplingPort 
            Name="IP_SP_FDAS_PEERA_XTALK"  
            Attribute="LOCAL_PORT"
            Direction="DESTINATION"
            MessageSize="96"
            RefreshRate="0.05"/>
        
        <SamplingPort 
            Name="IP_SP_FADEC_L_CHA_MSG3_FDAS"  
            Attribute="LOCAL_PORT"
            Direction="DESTINATION"
            MessageSize="88"
            RefreshRate="0.15"/>
        
        <SamplingPort 
            Name="IP_SP_FADEC_L_CHB_MSG3_FDAS"  
            Attribute="LOCAL_PORT"
            Direction="DESTINATION"
            MessageSize="88"
            RefreshRate="0.15"/>
        
        <SamplingPort 
            Name="IP_SP_FADEC_R_CHA_MSG3_FDAS"  
            Attribute="LOCAL_PORT"
            Direction="DESTINATION"
            MessageSize="88"
            RefreshRate="0.15"/>
        
        <SamplingPort 
            Name="IP_SP_FADEC_R_CHB_MSG3_FDAS"  
            Attribute="LOCAL_PORT"
            Direction="DESTINATION"
            MessageSize="88"
            RefreshRate="0.15"/>
        
        <SamplingPort 
            Name="IP_QP_FCM_1_04AF20_TO_FDAS"  
            Attribute="LOCAL_PORT"
            Direction="DESTINATION"
            MessageSize="156"
            RefreshRate="0.15"/>
        
        <QueuingPort 
            Name="IP_QP_FCM_1_03_TO_FDAS"  
            QueueLength="2"
            MessageSize="396" 
            Direction="DESTINATION"
            Protocol="NOT_APPLICABLE"             
            Attribute="LOCAL_PORT"/>

        <SamplingPort 
            Name="IP_QP_FCM_2_04AF20_TO_FDAS"  
            Attribute="LOCAL_PORT"
            Direction="DESTINATION"
            MessageSize="156"
            RefreshRate="0.15"/>
        
        <QueuingPort 
            Name="IP_QP_FCM_2_03_TO_FDAS"  
            QueueLength="2"
            MessageSize="396" 
            Direction="DESTINATION"
            Protocol="NOT_APPLICABLE"             
            Attribute="LOCAL_PORT"/>

        <SamplingPort 
            Name="IP_QP_FCM_3_04AF20_TO_FDAS"  
            Attribute="LOCAL_PORT"
            Direction="DESTINATION"
            MessageSize="156"
            RefreshRate="0.15"/>
        
        <QueuingPort 
            Name="IP_QP_FCM_3_03_TO_FDAS"  
            QueueLength="2"
            MessageSize="396" 
            Direction="DESTINATION"
            Protocol="NOT_APPLICABLE"             
            Attribute="LOCAL_PORT"/>

        <SamplingPort 
            Name="IP_SP_ISS_124_TO_FDAS_L"  
            Attribute="LOCAL_PORT"
            Direction="DESTINATION"
            MessageSize="76"
            RefreshRate="0.15"/>
        
        <SamplingPort 
            Name="IP_SP_ISS_136_TO_FDAS_L"  
            Attribute="LOCAL_PORT"
            Direction="DESTINATION"
            MessageSize="60"
            RefreshRate="0.3"/>
        
        <SamplingPort 
            Name="IP_SP_ISS_125_TO_FDAS_L"  
            Attribute="LOCAL_PORT"
            Direction="DESTINATION"
            MessageSize="52"
            RefreshRate="0.06"/>
        
        <SamplingPort 
            Name="IP_SP_ISS_129_TO_FDAS_L"  
            Attribute="LOCAL_PORT"
            Direction="DESTINATION"
            MessageSize="132"
            RefreshRate="0.6"/>
        
        <SamplingPort 
            Name="IP_SP_ISS_103_TO_FDAS_R"  
            Attribute="LOCAL_PORT"
            Direction="DESTINATION"
            MessageSize="76"
            RefreshRate="0.15"/>
        
        <SamplingPort 
            Name="IP_SP_ISS_109_TO_FDAS_R"  
            Attribute="LOCAL_PORT"
            Direction="DESTINATION"
            MessageSize="60"
            RefreshRate="0.3"/>
        
        <SamplingPort 
            Name="IP_SP_ISS_104_TO_FDAS_R"  
            Attribute="LOCAL_PORT"
            Direction="DESTINATION"
            MessageSize="52"
            RefreshRate="0.6"/>
        
        <SamplingPort 
            Name="IP_SP_ISS_108_TO_FDAS_R"  
            Attribute="LOCAL_PORT"
            Direction="DESTINATION"
            MessageSize="132"
            RefreshRate="0.6"/>
        
        <SamplingPort 
            Name="IP_SP_RPDU_UP_1A_LB_100_FDAS"  
            Attribute="LOCAL_PORT"
            Direction="DESTINATION"
            MessageSize="196"
            RefreshRate="0.3"/>
        
        <SamplingPort 
            Name="IP_SP_RPDU_UP_1A_LG_100_FDAS"  
            Attribute="LOCAL_PORT"
            Direction="DESTINATION"
            MessageSize="84"
            RefreshRate="0.3"/>
        
        <SamplingPort 
            Name="IP_SP_RPDU_UP_1A_RAS_100_FDAS"  
            Attribute="LOCAL_PORT"
            Direction="DESTINATION"
            MessageSize="44"
            RefreshRate="0.3"/>
        
        <SamplingPort 
            Name="IP_SP_RPDU_UP_1A_RB_100_FDAS"  
            Attribute="LOCAL_PORT"
            Direction="DESTINATION"
            MessageSize="180"
            RefreshRate="0.3"/>
        
        <SamplingPort 
            Name="IP_SP_RPDU_UP_1A_RG_100_FDAS"  
            Attribute="LOCAL_PORT"
            Direction="DESTINATION"
            MessageSize="84"
            RefreshRate="0.3"/>
        
        <SamplingPort 
            Name="IP_SP_RPDU_UP_1B_LB_100_FDAS"  
            Attribute="LOCAL_PORT"
            Direction="DESTINATION"
            MessageSize="196"
            RefreshRate="0.3"/>
        
        <SamplingPort 
            Name="IP_SP_RPDU_UP_1B_LG_100_FDAS"  
            Attribute="LOCAL_PORT"
            Direction="DESTINATION"
            MessageSize="84"
            RefreshRate="0.3"/>
        
        <SamplingPort 
            Name="IP_SP_RPDU_UP_1B_RAS_100_FDAS"  
            Attribute="LOCAL_PORT"
            Direction="DESTINATION"
            MessageSize="44"
            RefreshRate="0.3"/>
        
        <SamplingPort 
            Name="IP_SP_RPDU_UP_1B_RB_100_FDAS"  
            Attribute="LOCAL_PORT"
            Direction="DESTINATION"
            MessageSize="180"
            RefreshRate="0.3"/>
        
        <SamplingPort 
            Name="IP_SP_RPDU_UP_1B_RG_100_FDAS"  
            Attribute="LOCAL_PORT"
            Direction="DESTINATION"
            MessageSize="84"
            RefreshRate="0.3"/>
        
        <SamplingPort 
            Name="IP_SP_RPDU_UP_2A_LB_100_FDAS"  
            Attribute="LOCAL_PORT"
            Direction="DESTINATION"
            MessageSize="196"
            RefreshRate="0.3"/>
        
        <SamplingPort 
            Name="IP_SP_RPDU_UP_2A_LG_100_FDAS"  
            Attribute="LOCAL_PORT"
            Direction="DESTINATION"
            MessageSize="84"
            RefreshRate="0.3"/>
        
        <SamplingPort 
            Name="IP_SP_RPDU_UP_2A_RAS_100_FDAS"  
            Attribute="LOCAL_PORT"
            Direction="DESTINATION"
            MessageSize="44"
            RefreshRate="0.3"/>
        
        <SamplingPort 
            Name="IP_SP_RPDU_UP_2A_RB_100_FDAS"  
            Attribute="LOCAL_PORT"
            Direction="DESTINATION"
            MessageSize="180"
            RefreshRate="0.3"/>
        
        <SamplingPort 
            Name="IP_SP_RPDU_UP_2A_RG_100_FDAS"  
            Attribute="LOCAL_PORT"
            Direction="DESTINATION"
            MessageSize="84"
            RefreshRate="0.3"/>
        
        <SamplingPort 
            Name="IP_SP_RPDU_UP_2A_SG_2_FDAS"  
            Attribute="LOCAL_PORT"
            Direction="DESTINATION"
            MessageSize="212"
            RefreshRate="0.3"/>
        
        <SamplingPort 
            Name="IP_SP_RPDU_UP_2B_LB_100_FDAS"  
            Attribute="LOCAL_PORT"
            Direction="DESTINATION"
            MessageSize="196"
            RefreshRate="0.3"/>
        
        <SamplingPort 
            Name="IP_SP_RPDU_UP_2B_LG_100_FDAS"  
            Attribute="LOCAL_PORT"
            Direction="DESTINATION"
            MessageSize="84"
            RefreshRate="0.3"/>
        
        <SamplingPort 
            Name="IP_SP_RPDU_UP_2B_RAS_100_FDAS"  
            Attribute="LOCAL_PORT"
            Direction="DESTINATION"
            MessageSize="44"
            RefreshRate="0.3"/>
        
        <SamplingPort 
            Name="IP_SP_RPDU_UP_2B_RB_100_FDAS"  
            Attribute="LOCAL_PORT"
            Direction="DESTINATION"
            MessageSize="180"
            RefreshRate="0.3"/>
        
        <SamplingPort 
            Name="IP_SP_RPDU_UP_2B_RG_100_FDAS"  
            Attribute="LOCAL_PORT"
            Direction="DESTINATION"
            MessageSize="84"
            RefreshRate="0.3"/>
        
        <SamplingPort 
            Name="IP_SP_RPDU_UP_2B_SG_2_FDAS"  
            Attribute="LOCAL_PORT"
            Direction="DESTINATION"
            MessageSize="212"
            RefreshRate="0.3"/>
        
        <SamplingPort 
            Name="IP_SP_FROM_DMI_1_TO_FDAS"  
            Attribute="LOCAL_PORT"
            Direction="DESTINATION"
            MessageSize="104"
            RefreshRate="0.1"/>
        
        <SamplingPort 
            Name="IP_SP_FROM_DMI_3_TO_FDAS"  
            Attribute="LOCAL_PORT"
            Direction="DESTINATION"
            MessageSize="104"
            RefreshRate="0.1"/>
        
        <SamplingPort 
            Name="IP_SP_FROM_DMI_2_TO_FDAS"  
            Attribute="LOCAL_PORT"
            Direction="DESTINATION"
            MessageSize="104"
            RefreshRate="0.1"/>
        
        <SamplingPort 
            Name="IP_SP_MCMW_1_C_PREE_CHA_FDAS"  
            Attribute="LOCAL_PORT"
            Direction="DESTINATION"
            MessageSize="48"
            RefreshRate="0.15"/>
        
        <SamplingPort 
            Name="IP_SP_MCMW_2_C_PREE_CHA_FDAS"  
            Attribute="LOCAL_PORT"
            Direction="DESTINATION"
            MessageSize="48"
            RefreshRate="0.15"/>
        
        <SamplingPort 
            Name="IP_SP_WHCC_TX1_TO_FDAS"  
            Attribute="LOCAL_PORT"
            Direction="DESTINATION"
            MessageSize="56"
            RefreshRate="3.0"/>
        
        <SamplingPort 
            Name="IP_SP_LGCU2_CONCH_TO_FDAS"  
            Attribute="LOCAL_PORT"
            Direction="DESTINATION"
            MessageSize="88"
            RefreshRate="0.3"/>
        
        <SamplingPort 
            Name="IP_SP_FUELO_1OffB_FDAS"  
            Attribute="LOCAL_PORT"
            Direction="DESTINATION"
            MessageSize="116"
            RefreshRate="0.3"/>
        
        <SamplingPort 
            Name="IP_SP_L_ID_STATUS_TO_FDAS"  
            Attribute="LOCAL_PORT"
            Direction="DESTINATION"
            MessageSize="48"
            RefreshRate="0.3"/>
        
        <SamplingPort 
            Name="IP_SP_L_NAI_SW1_OFF_TO_FDAS"  
            Attribute="LOCAL_PORT"
            Direction="DESTINATION"
            MessageSize="52"
            RefreshRate="0.3"/>
        
        <SamplingPort 
            Name="IP_SP_EMER_01_Status_TO_FDAS"  
            Attribute="LOCAL_PORT"
            Direction="DESTINATION"
            MessageSize="44"
            RefreshRate="0.3"/>
        
        <SamplingPort 
            Name="IP_SP_RFS_80_L_TO_FDAS"  
            Attribute="LOCAL_PORT"
            Direction="DESTINATION"
            MessageSize="44"
            RefreshRate="0.3"/>
        
        <SamplingPort 
            Name="IP_SP_ICE_CSSM_1_TO_FDAS"  
            Attribute="LOCAL_PORT"
            Direction="DESTINATION"
            MessageSize="72"
            RefreshRate="0.3"/>
        
        <SamplingPort 
            Name="IP_SP_ENGIN_R_ARMED_FDAS"  
            Attribute="LOCAL_PORT"
            Direction="DESTINATION"
            MessageSize="72"
            RefreshRate="0.3"/>
        
        <SamplingPort 
            Name="IP_SP_R_ID_DISC_TO_FDAS"  
            Attribute="LOCAL_PORT"
            Direction="DESTINATION"
            MessageSize="48"
            RefreshRate="0.3"/>
        
        <SamplingPort 
            Name="IP_SP_R_NAI_SW1_OFF_TO_FDAS"  
            Attribute="LOCAL_PORT"
            Direction="DESTINATION"
            MessageSize="52"
            RefreshRate="0.3"/>
        
        <SamplingPort 
            Name="IP_SP_MCMW_2_C_PREE_CHB_FDAS"  
            Attribute="LOCAL_PORT"
            Direction="DESTINATION"
            MessageSize="48"
            RefreshRate="0.15"/>
        
        <SamplingPort 
            Name="IP_SP_WHCA_TX1_TO_FDAS"  
            Attribute="LOCAL_PORT"
            Direction="DESTINATION"
            MessageSize="68"
            RefreshRate="3.0"/>
        
        <SamplingPort 
            Name="IP_SP_FUELO_1OffA_FDAS"  
            Attribute="LOCAL_PORT"
            Direction="DESTINATION"
            MessageSize="116"
            RefreshRate="0.3"/>
        
        <SamplingPort 
            Name="IP_SP_L_NAI_SW2_OFF_TO_FDAS"  
            Attribute="LOCAL_PORT"
            Direction="DESTINATION"
            MessageSize="52"
            RefreshRate="0.3"/>
        
        <SamplingPort 
            Name="IP_SP_MCMW_1_C_PREE_CHB_FDAS"  
            Attribute="LOCAL_PORT"
            Direction="DESTINATION"
            MessageSize="48"
            RefreshRate="0.15"/>
        
        <SamplingPort 
            Name="IP_SP_EMER_02_Status_TO_FDAS"  
            Attribute="LOCAL_PORT"
            Direction="DESTINATION"
            MessageSize="44"
            RefreshRate="0.3"/>
        
        <SamplingPort 
            Name="IP_SP_ACU_CALL_TO_FDAS"  
            Attribute="LOCAL_PORT"
            Direction="DESTINATION"
            MessageSize="48"
            RefreshRate="0.3"/>
        
        <SamplingPort 
            Name="IP_SP_WHCB_TX1_TO_FDAS"  
            Attribute="LOCAL_PORT"
            Direction="DESTINATION"
            MessageSize="64"
            RefreshRate="3.0"/>
        
        <SamplingPort 
            Name="IP_SP_IASC2_OA_1000_TO_FDAS_1"  
            Attribute="LOCAL_PORT"
            Direction="DESTINATION"
            MessageSize="136"
            RefreshRate="3.0"/>
        
        <SamplingPort 
            Name="IP_SP_IASC2_OA_500_TO_FDAS_1"  
            Attribute="LOCAL_PORT"
            Direction="DESTINATION"
            MessageSize="124"
            RefreshRate="1.5"/>
        
        <SamplingPort 
            Name="IP_SP_IASC2_OB_1000_TO_FDAS_1"  
            Attribute="LOCAL_PORT"
            Direction="DESTINATION"
            MessageSize="76"
            RefreshRate="3.0"/>
        
        <SamplingPort 
            Name="IP_SP_IASC2_OB_500_TO_FDAS_1"  
            Attribute="LOCAL_PORT"
            Direction="DESTINATION"
            MessageSize="84"
            RefreshRate="1.5"/>
        
        <SamplingPort 
            Name="IP_SP_IASC1_OB_200_TO_FDAS_06"  
            Attribute="LOCAL_PORT"
            Direction="DESTINATION"
            MessageSize="52"
            RefreshRate="3.0"/>
        
        <SamplingPort 
            Name="IP_SP_IASC2_OB_200_FDAS_1_07"  
            Attribute="LOCAL_PORT"
            Direction="DESTINATION"
            MessageSize="52"
            RefreshRate="1.5"/>
        
        <SamplingPort 
            Name="IP_SP_ABCU_TX1_TO_FDAS"  
            Attribute="LOCAL_PORT"
            Direction="DESTINATION"
            MessageSize="116"
            RefreshRate="0.3"/>
        
        <SamplingPort 
            Name="IP_SP_BCMU_TX1_TO_FDAS"  
            Attribute="LOCAL_PORT"
            Direction="DESTINATION"
            MessageSize="144"
            RefreshRate="0.3"/>
        
        <SamplingPort 
            Name="IP_SP_ICE_CSSM_2_TO_FDAS"  
            Attribute="LOCAL_PORT"
            Direction="DESTINATION"
            MessageSize="76"
            RefreshRate="0.3"/>
        
        <SamplingPort 
            Name="IP_SP_R_NAI_SW2_OFF_TO_FDAS"  
            Attribute="LOCAL_PORT"
            Direction="DESTINATION"
            MessageSize="52"
            RefreshRate="0.3"/>
        
        <SamplingPort 
            Name="IP_SP_ENGIN_ARMED_FDAS"  
            Attribute="LOCAL_PORT"
            Direction="DESTINATION"
            MessageSize="72"
            RefreshRate="0.3"/>
        
        <SamplingPort 
            Name="IP_SP_FUEL_1_250_FDAS"  
            Attribute="LOCAL_PORT"
            Direction="DESTINATION"
            MessageSize="44"
            RefreshRate="0.75"/>
        
        <SamplingPort 
            Name="IP_SP_FUEL_29_A1_FDAS"  
            Attribute="LOCAL_PORT"
            Direction="DESTINATION"
            MessageSize="516"
            RefreshRate="3.0"/>
        
        <SamplingPort 
            Name="IP_SP_FUEL_1B_250_FDAS"  
            Attribute="LOCAL_PORT"
            Direction="DESTINATION"
            MessageSize="44"
            RefreshRate="0.75"/>
        
        <SamplingPort 
            Name="IP_SP_FUEL_29_B1_FDAS"  
            Attribute="LOCAL_PORT"
            Direction="DESTINATION"
            MessageSize="516"
            RefreshRate="3.0"/>
        
        <SamplingPort 
            Name="IP_SP_IASC1_OA_1000_TO_FDAS_1"  
            Attribute="LOCAL_PORT"
            Direction="DESTINATION"
            MessageSize="152"
            RefreshRate="3.0"/>
        
        <SamplingPort 
            Name="IP_SP_IASC1_OA_500_TO_FDAS_1"  
            Attribute="LOCAL_PORT"
            Direction="DESTINATION"
            MessageSize="124"
            RefreshRate="1.5"/>
        
        <SamplingPort 
            Name="IP_SP_IASC1_OB_1000_TO_FDAS_1"  
            Attribute="LOCAL_PORT"
            Direction="DESTINATION"
            MessageSize="144"
            RefreshRate="3.0"/>
        
        <SamplingPort 
            Name="IP_SP_IASC1_OB_500_TO_FDAS_1"  
            Attribute="LOCAL_PORT"
            Direction="DESTINATION"
            MessageSize="124"
            RefreshRate="1.5"/>
        
        <SamplingPort 
            Name="IP_SP_IASC1_OB_200_TO_FDAS_07"  
            Attribute="LOCAL_PORT"
            Direction="DESTINATION"
            MessageSize="52"
            RefreshRate="3.0"/>
        
        <SamplingPort 
            Name="IP_SP_IASC2_OB_200_FDAS_1_09"  
            Attribute="LOCAL_PORT"
            Direction="DESTINATION"
            MessageSize="52"
            RefreshRate="1.5"/>
        
        <SamplingPort 
            Name="IP_SP_IHDC_A_TO_FDAS"  
            Attribute="LOCAL_PORT"
            Direction="DESTINATION"
            MessageSize="72"
            RefreshRate="0.3"/>
        
        <SamplingPort 
            Name="IP_SP_HF_GIPC_CH_INST_TO_FDAS"  
            Attribute="LOCAL_PORT"
            Direction="DESTINATION"
            MessageSize="44"
            RefreshRate="0.3"/>
        
        <SamplingPort 
            Name="IP_SP_LGCU1_CONCH_20_TO_FDAS"  
            Attribute="LOCAL_PORT"
            Direction="DESTINATION"
            MessageSize="44"
            RefreshRate="0.06"/>
        
        <SamplingPort 
            Name="IP_SP_LGCU1_CONCH_TO_FDAS"  
            Attribute="LOCAL_PORT"
            Direction="DESTINATION"
            MessageSize="88"
            RefreshRate="0.3"/>
        
        <SamplingPort 
            Name="IP_SP_IASC1_OA_500_FDAS_2"  
            Attribute="LOCAL_PORT"
            Direction="DESTINATION"
            MessageSize="48"
            RefreshRate="3.0"/>
        
        <SamplingPort 
            Name="IP_SP_IASC1_OA_500_TO_FDAS_2"  
            Attribute="LOCAL_PORT"
            Direction="DESTINATION"
            MessageSize="68"
            RefreshRate="1.5"/>
        
        <SamplingPort 
            Name="IP_SP_IASC1_OB_1000_TO_FDAS_2"  
            Attribute="LOCAL_PORT"
            Direction="DESTINATION"
            MessageSize="48"
            RefreshRate="3.0"/>
        
        <SamplingPort 
            Name="IP_SP_IASC1_OB_500_TO_FDAS_2"  
            Attribute="LOCAL_PORT"
            Direction="DESTINATION"
            MessageSize="68"
            RefreshRate="1.5"/>
        
        <SamplingPort 
            Name="IP_SP_PSEU_CH_B_200_TO_FDAS"  
            Attribute="LOCAL_PORT"
            Direction="DESTINATION"
            MessageSize="68"
            RefreshRate="0.6"/>
        
        <SamplingPort 
            Name="IP_SP_PSEU_CH_B_TO_FDAS"  
            Attribute="LOCAL_PORT"
            Direction="DESTINATION"
            MessageSize="44"
            RefreshRate="0.3"/>
        
        <SamplingPort 
            Name="IP_SP_APU_S_PUMPC_FDAS"  
            Attribute="LOCAL_PORT"
            Direction="DESTINATION"
            MessageSize="52"
            RefreshRate="0.3"/>
        
        <SamplingPort 
            Name="IP_SP_TPT_GEA_1_TO_FDAS"  
            Attribute="LOCAL_PORT"
            Direction="DESTINATION"
            MessageSize="56"
            RefreshRate="0.3"/>
        
        <SamplingPort 
            Name="IP_SP_FSECU_1_MON_TO_FDAS"  
            Attribute="LOCAL_PORT"
            Direction="DESTINATION"
            MessageSize="68"
            RefreshRate="6.0"/>
        
        <SamplingPort 
            Name="IP_SP_FUEL_1_250_FDAS_2"  
            Attribute="LOCAL_PORT"
            Direction="DESTINATION"
            MessageSize="44"
            RefreshRate="0.75"/>
        
        <SamplingPort 
            Name="IP_SP_FUEL_29_A1_FDAS_2"  
            Attribute="LOCAL_PORT"
            Direction="DESTINATION"
            MessageSize="44"
            RefreshRate="3.0"/>
        
        <SamplingPort 
            Name="IP_SP_FUEL_1B_250_FDAS_2"  
            Attribute="LOCAL_PORT"
            Direction="DESTINATION"
            MessageSize="44"
            RefreshRate="0.75"/>
        
        <SamplingPort 
            Name="IP_SP_FUEL_29_B1_FDAS_2"  
            Attribute="LOCAL_PORT"
            Direction="DESTINATION"
            MessageSize="44"
            RefreshRate="3.0"/>
        
        <SamplingPort 
            Name="IP_SP_IASC2_OA_1000_TO_FDAS_2"  
            Attribute="LOCAL_PORT"
            Direction="DESTINATION"
            MessageSize="48"
            RefreshRate="3.0"/>
        
        <SamplingPort 
            Name="IP_SP_IASC2_OA_500_TO_FDAS_2"  
            Attribute="LOCAL_PORT"
            Direction="DESTINATION"
            MessageSize="68"
            RefreshRate="1.5"/>
        
        <SamplingPort 
            Name="IP_SP_IASC2_OB_1000_TO_FDAS_2"  
            Attribute="LOCAL_PORT"
            Direction="DESTINATION"
            MessageSize="48"
            RefreshRate="3.0"/>
        
        <SamplingPort 
            Name="IP_SP_IASC2_OB_500_TO_FDAS_2"  
            Attribute="LOCAL_PORT"
            Direction="DESTINATION"
            MessageSize="68"
            RefreshRate="1.5"/>
        
        <SamplingPort 
            Name="IP_SP_HYDIMC_1A_2000_TO_FDAS"  
            Attribute="LOCAL_PORT"
            Direction="DESTINATION"
            MessageSize="108"
            RefreshRate="6.0"/>
        
        <SamplingPort 
            Name="IP_SP_HYDIMC_1A_TO_FDAS"  
            Attribute="LOCAL_PORT"
            Direction="DESTINATION"
            MessageSize="168"
            RefreshRate="0.3"/>
        
        <SamplingPort 
            Name="IP_SP_L_FRD_PUMPCON_2_FDAS"  
            Attribute="LOCAL_PORT"
            Direction="DESTINATION"
            MessageSize="56"
            RefreshRate="0.3"/>
        
        <SamplingPort 
            Name="IP_SP_FSECU_2_CMD_TO_FDAS"  
            Attribute="LOCAL_PORT"
            Direction="DESTINATION"
            MessageSize="68"
            RefreshRate="6.0"/>
        
        <SamplingPort 
            Name="IP_SP_PSEU_CH_A_200_TO_FDAS"  
            Attribute="LOCAL_PORT"
            Direction="DESTINATION"
            MessageSize="68"
            RefreshRate="0.6"/>
        
        <SamplingPort 
            Name="IP_SP_PSEU_CH_A_TO_FDAS"  
            Attribute="LOCAL_PORT"
            Direction="DESTINATION"
            MessageSize="44"
            RefreshRate="0.3"/>
        
        <SamplingPort 
            Name="IP_SP_HYDIMC_2B_2000_TO_FDAS"  
            Attribute="LOCAL_PORT"
            Direction="DESTINATION"
            MessageSize="112"
            RefreshRate="6.0"/>
        
        <SamplingPort 
            Name="IP_SP_HYDIMC_2B_TO_FDAS"  
            Attribute="LOCAL_PORT"
            Direction="DESTINATION"
            MessageSize="184"
            RefreshRate="0.3"/>
        
        <SamplingPort 
            Name="IP_SP_XFEED_losed_FDAS"  
            Attribute="LOCAL_PORT"
            Direction="DESTINATION"
            MessageSize="48"
            RefreshRate="0.3"/>
        
        <SamplingPort 
            Name="IP_SP_RFS_80_R_TO_FDAS"  
            Attribute="LOCAL_PORT"
            Direction="DESTINATION"
            MessageSize="44"
            RefreshRate="0.3"/>
        
        <SamplingPort 
            Name="IP_SP_L_AFT_PS_tatus_FDAS"  
            Attribute="LOCAL_PORT"
            Direction="DESTINATION"
            MessageSize="88"
            RefreshRate="0.3"/>
        
        <SamplingPort 
            Name="IP_SP_EMP1B_ANA_TO_FDAS"  
            Attribute="LOCAL_PORT"
            Direction="DESTINATION"
            MessageSize="44"
            RefreshRate="0.3"/>
        
        <SamplingPort 
            Name="IP_SP_IHDC_B_TO_FDAS"  
            Attribute="LOCAL_PORT"
            Direction="DESTINATION"
            MessageSize="72"
            RefreshRate="0.3"/>
        
        <SamplingPort 
            Name="IP_SP_R_AFT_PS_tatus_FDAS"  
            Attribute="LOCAL_PORT"
            Direction="DESTINATION"
            MessageSize="72"
            RefreshRate="0.3"/>
        
        <SamplingPort 
            Name="IP_SP_LRA_R_ALTTD_2_FDAS"  
            Attribute="LOCAL_PORT"
            Direction="DESTINATION"
            MessageSize="52"
            RefreshRate="0.075"/>
        
        <SamplingPort 
            Name="IP_SP_ECU_1_200_FDAS"  
            Attribute="LOCAL_PORT"
            Direction="DESTINATION"
            MessageSize="152"
            RefreshRate="0.6"/>
        
        <SamplingPort 
            Name="IP_SP_FSECU_1_CMD_TO_FDAS"  
            Attribute="LOCAL_PORT"
            Direction="DESTINATION"
            MessageSize="68"
            RefreshRate="6.0"/>
        
        <SamplingPort 
            Name="IP_SP_LRA_L_ALTTD_2_FDAS"  
            Attribute="LOCAL_PORT"
            Direction="DESTINATION"
            MessageSize="52"
            RefreshRate="0.075"/>
        
        <SamplingPort 
            Name="IP_SP_ECU_2_MSG_200_TO_FDAS_2"  
            Attribute="LOCAL_PORT"
            Direction="DESTINATION"
            MessageSize="52"
            RefreshRate="0.6"/>
        
        <SamplingPort 
            Name="IP_SP_RSVR1_LO_TO_FDAS"  
            Attribute="LOCAL_PORT"
            Direction="DESTINATION"
            MessageSize="48"
            RefreshRate="0.3"/>
        
        <SamplingPort 
            Name="IP_SP_FSECU_2_MON_TO_FDAS"  
            Attribute="LOCAL_PORT"
            Direction="DESTINATION"
            MessageSize="68"
            RefreshRate="6.0"/>
        
        <SamplingPort 
            Name="IP_SP_RSVR2_LO_TO_FDAS"  
            Attribute="LOCAL_PORT"
            Direction="DESTINATION"
            MessageSize="52"
            RefreshRate="0.3"/>
        

        <SamplingPort 
            Name="OP_SP_FDAS_COS_TO_OMS"  
            Attribute="LOCAL_PORT"
            Direction="SOURCE"
            MessageSize="20"
            RefreshRate="2.0"/>
        
        <QueuingPort 
            Name="OP_SP_MCAST_ALERTS"  
            QueueLength="2"
            MessageSize="2152" 
            Direction="SOURCE"
            Protocol="RECEIVER_DISCARD"
            Attribute="LOCAL_PORT"/>

        <SamplingPort 
            Name="OP_SP_MCAST_GENERAL"  
            Attribute="LOCAL_PORT"
            Direction="SOURCE"
            MessageSize="188"
            RefreshRate="0.05"/>
        
        <SamplingPort 
            Name="OP_SP_MCAST_ISS_DATA"  
            Attribute="LOCAL_PORT"
            Direction="SOURCE"
            MessageSize="168"
            RefreshRate="0.05"/>
        
        <SamplingPort 
            Name="OP_SP_XTALK"  
            Attribute="LOCAL_PORT"
            Direction="SOURCE"
            MessageSize="64"
            RefreshRate="0.05"/>
        
        <SamplingPort 
            Name="OP_SP_MWC_CMDS"  
            Attribute="LOCAL_PORT"
            Direction="SOURCE"
            MessageSize="140"
            RefreshRate="0.05"/>
        
</A664ApplicationPorts>